odoo/addons/mail_environment_google_gmail/README.rst
odoo/addons/mail_environment_google_gmail/__init__.py
odoo/addons/mail_environment_google_gmail/__manifest__.py
odoo/addons/mail_environment_google_gmail/i18n/it.po
odoo/addons/mail_environment_google_gmail/i18n/mail_environment_google_gmail.pot
odoo/addons/mail_environment_google_gmail/i18n/sv.po
odoo/addons/mail_environment_google_gmail/models/__init__.py
odoo/addons/mail_environment_google_gmail/models/ir_mail_server.py
odoo/addons/mail_environment_google_gmail/readme/CONFIGURE.md
odoo/addons/mail_environment_google_gmail/readme/CONTRIBUTORS.md
odoo/addons/mail_environment_google_gmail/readme/DESCRIPTION.md
odoo/addons/mail_environment_google_gmail/static/description/icon.png
odoo/addons/mail_environment_google_gmail/static/description/index.html
odoo_addon_mail_environment_google_gmail-18.0.1.0.0.4.dist-info/METADATA
odoo_addon_mail_environment_google_gmail-18.0.1.0.0.4.dist-info/WHEEL
odoo_addon_mail_environment_google_gmail-18.0.1.0.0.4.dist-info/top_level.txt
odoo_addon_mail_environment_google_gmail-18.0.1.0.0.4.dist-info/RECORD
